<?xml version="1.0" encoding="UTF-8"?>
<locale>
    <app>
        <title>Servidor de debate Agade</title>
        <passwordinput>Contraseña maestra</passwordinput>
        <passwordinputchrono>Contraseña de cronometro</passwordinputchrono>
        <okbutton>Aceptar</okbutton>
    </app>
    <ipinfo>
        <tabtitle>Informacion IP</tabtitle>
        <iplabel>IPs para esta maquina</iplabel>
        <firewallinfo>El firewall debe permitir que Java acepte conexiones entrantes</firewallinfo>
    </ipinfo>
    <chrono>
        <newchrono>Nuevo</newchrono>
        <see>Ver</see>
        <control>Control</control>
    </chrono>
</locale>