<?xml version="1.0" encoding="UTF-8"?>
<locale>
    <app>
        <title>Servidor de debate Agade</title>
        <passwordinputscore>Contraseña para puntuaciones</passwordinputscore>
        <passwordinputchrono>Contraseña para cronometro</passwordinputchrono>
        <okbutton>Aceptar</okbutton>
    </app>
    <ipinfo>
        <tabtitle>Informacion IP</tabtitle>
        <iplabel>IPs para esta maquina</iplabel>
        <firewallinfo>El firewall debe permitir que Java acepte conexiones entrantes</firewallinfo>
    </ipinfo>
    <chronoinfo>
        <tabtitle>Cronometros</tabtitle>
    </chronoinfo>
    <chrono>
        <newchrono>Nuevo</newchrono>
        <newsubmit>Ok</newsubmit>
        <see>Ver</see>
        <control>Control</control>
    </chrono>
</locale>